telepact_cli/__init__.py
telepact_cli/calculator.telepact.json
telepact_cli/cli.py
telepact_cli/telepact/Client.py
telepact_cli/telepact/DefaultSerialization.py
telepact_cli/telepact/Message.py
telepact_cli/telepact/MockServer.py
telepact_cli/telepact/MockTelepactSchema.py
telepact_cli/telepact/RandomGenerator.py
telepact_cli/telepact/Response.py
telepact_cli/telepact/Serialization.py
telepact_cli/telepact/SerializationError.py
telepact_cli/telepact/Serializer.py
telepact_cli/telepact/Server.py
telepact_cli/telepact/TelepactError.py
telepact_cli/telepact/TelepactSchema.py
telepact_cli/telepact/TelepactSchemaFiles.py
telepact_cli/telepact/TelepactSchemaParseError.py
telepact_cli/telepact/TestClient.py
telepact_cli/telepact/TypedMessage.py
telepact_cli/telepact/__init__.py
telepact_cli/telepact/internal/ClientHandleMessage.py
telepact_cli/telepact/internal/DeserializeInternal.py
telepact_cli/telepact/internal/HandleMessage.py
telepact_cli/telepact/internal/ParseRequestMessage.py
telepact_cli/telepact/internal/ProcessBytes.py
telepact_cli/telepact/internal/SelectStructFields.py
telepact_cli/telepact/internal/SerializeInternal.py
telepact_cli/telepact/internal/binary/Base64Encoder.py
telepact_cli/telepact/internal/binary/BinaryEncoder.py
telepact_cli/telepact/internal/binary/BinaryEncoderUnavailableError.py
telepact_cli/telepact/internal/binary/BinaryEncoding.py
telepact_cli/telepact/internal/binary/BinaryEncodingCache.py
telepact_cli/telepact/internal/binary/BinaryEncodingMissing.py
telepact_cli/telepact/internal/binary/BinaryPackNode.py
telepact_cli/telepact/internal/binary/CannotPack.py
telepact_cli/telepact/internal/binary/ClientBase64Decode.py
telepact_cli/telepact/internal/binary/ClientBase64Encode.py
telepact_cli/telepact/internal/binary/ClientBase64Encoder.py
telepact_cli/telepact/internal/binary/ClientBinaryDecode.py
telepact_cli/telepact/internal/binary/ClientBinaryEncode.py
telepact_cli/telepact/internal/binary/ClientBinaryEncoder.py
telepact_cli-1.0.0a174.dist-info/METADATA
telepact_cli-1.0.0a174.dist-info/WHEEL
telepact_cli-1.0.0a174.dist-info/entry_points.txt
telepact_cli-1.0.0a174.dist-info/licenses/LICENSE
telepact_cli-1.0.0a174.dist-info/licenses/NOTICE
telepact_cli-1.0.0a174.dist-info/RECORD
